pytorch_yard/__init__.py
pytorch_yard/core.py
pytorch_yard/py.typed
pytorch_yard/avalanche/__init__.py
pytorch_yard/avalanche/logger.py
pytorch_yard/avalanche/scenarios.py
pytorch_yard/avalanche/wandb.py
pytorch_yard/configs/__init__.py
pytorch_yard/configs/register.py
pytorch_yard/configs/cfg/__init__.py
pytorch_yard/configs/cfg/lightning.py
pytorch_yard/configs/hydra/hydra_logging/rich.yaml
pytorch_yard/configs/hydra/job_logging/rich.yaml
pytorch_yard/experiments/__init__.py
pytorch_yard/experiments/avalanche.py
pytorch_yard/experiments/lightning.py
pytorch_yard/experiments/pytorch.py
pytorch_yard/lightning/__init__.py
pytorch_yard/lightning/wandb.py
pytorch_yard/utils/__init__.py
pytorch_yard/utils/logging.py
pytorch_yard/utils/rundir.py
pytorch_yard-2023.1.20.dist-info/LICENSE
pytorch_yard-2023.1.20.dist-info/METADATA
pytorch_yard-2023.1.20.dist-info/WHEEL
pytorch_yard-2023.1.20.dist-info/top_level.txt
pytorch_yard-2023.1.20.dist-info/RECORD
